lambda_labs/__init__.py
lambda_labs/catalog.csv
lambda_labs/lambda_api.py
lambda_cli-1.0.1.dist-info/LICENSE
lambda_cli-1.0.1.dist-info/METADATA
lambda_cli-1.0.1.dist-info/WHEEL
lambda_cli-1.0.1.dist-info/entry_points.txt
lambda_cli-1.0.1.dist-info/top_level.txt
lambda_cli-1.0.1.dist-info/RECORD
