Metadata-Version: 2.1
Name: lambda-cli
Version: 1.0.1
Summary: Lambda Labs instance management
Home-page: https://github.com/gmittal/lambda-cli
Author: Gautam Mittal
License: UNKNOWN
Keywords: development
Platform: UNKNOWN
Requires-Dist: colorama
Requires-Dist: fire
Requires-Dist: jinja2
Requires-Dist: pandas
Requires-Dist: pendulum
Requires-Dist: petname
Requires-Dist: prettytable
Requires-Dist: pyppeteer
